comis/__init__.py
comis/checks.py
comis/filters/__init__.py
comis/filters/author.py
comis/filters/flair.py
comis/filters/karma.py
comis/filters/time.py
comis/main.py
comis/py.typed
comis/utils/__init__.py
comis-0.1.1.dist-info/LICENSE
comis-0.1.1.dist-info/WHEEL
comis-0.1.1.dist-info/METADATA
comis-0.1.1.dist-info/RECORD
